CHANGELOG.txt
MANIFEST.in
README.md
_LICENSE.txt
setup.py
polytest/__init__.py
polytest/authorization.py
polytest/business_logic_doc.py
polytest/business_scenarios.py
polytest/error_handler.py
polytest/executor.py
polytest/helper.py
polytest/manager_commands.py
polytest/olap_commands.py
polytest/precondition.py
polytest/requirements.txt
polytest.egg-info/PKG-INFO
polytest.egg-info/SOURCES.txt
polytest.egg-info/dependency_links.txt
polytest.egg-info/requires.txt
polytest.egg-info/top_level.txt
polytest/logs/log-2020-12-01.log
polytest/tests/MyCube_Countries_import.csv
polytest/tests/__init__.py
polytest/tests/run_unit_tests.bat
polytest/tests/savinov_sphere_0_20-05-28_12_39_29.xlsx
polytest/tests/tests_poly.py