Metadata-Version: 1.1
Name: polytest
Version: 0.0.4
Summary: Wrapper for Polymatica API
Home-page: https://www.polymatica.com
Author: Polymatica
Author-email: k.savinov@polymatica.com
License: UNKNOWN
Keywords: polymatica
Platform: UNKNOWN
Classifier: Development Status :: 5 - Production/Stable
Classifier: Intended Audience :: Education
Classifier: Operating System :: Microsoft :: Windows :: Windows 10
Classifier: Programming Language :: Python :: 3
